NTPKKP/__init__.py
NTPKKP/activations.py
NTPKKP/layers.py
NTPKKP/losses.py
NTPKKP/network.py
NTPKKP/network_save_and_load.py
NTPKKP/train.py
NTkpp-0.0.3.4.1.dist-info/METADATA
NTkpp-0.0.3.4.1.dist-info/WHEEL
NTkpp-0.0.3.4.1.dist-info/top_level.txt
NTkpp-0.0.3.4.1.dist-info/RECORD
