Metadata-Version: 2.1
Name: NTkpp
Version: 0.0.3.4.1
Summary: Простая библиотека для полносвязных нейронных сетей
Author: Тихонов Иван
Author-email: tihonovivan737@gmail.com
Requires-Python: >=3.6
Requires-Dist: numpy
